numerology/__init__.py
numerology/locale/en/LC_MESSAGES/numerology.mo
numerology/locale/en/LC_MESSAGES/numerology.po
numerology/locale/fr/LC_MESSAGES/numerology.mo
numerology/locale/fr/LC_MESSAGES/numerology.po
numerology/main.py
numerology/numerology.pot
numerology/pythagorean/__init__.py
numerology/pythagorean/colors.py
numerology/pythagorean/common.py
numerology/pythagorean/interpretations.py
numerology/pythagorean/meanings/__init__.py
numerology/pythagorean/meanings/life_path.py
numerology/pythagorean/numerology.py
numerology-1.8.dist-info/entry_points.txt
numerology-1.8.dist-info/WHEEL
numerology-1.8.dist-info/METADATA
numerology-1.8.dist-info/RECORD
