Metadata-Version: 2.1
Name: numerology
Version: 1.8
Summary: Simple numerology tool to have fun with your friends.
Home-page: https://github.com/compuuteio/numerology
License: Apache-2.0
Keywords: numerology,pythagorean,vedic,clairvoyance,voyance
Author: Emmanuel GUENOU
Author-email: emmanuel@compuute.io
Maintainer: Emmanuel GUENOU
Maintainer-email: emmanuel@compuute.io
Requires-Python: >=3.8,<4.0
Classifier: License :: OSI Approved :: Apache Software License
Classifier: Programming Language :: Python :: 3
Classifier: Programming Language :: Python :: 3.10
Classifier: Programming Language :: Python :: 3.8
Classifier: Programming Language :: Python :: 3.9
Classifier: Topic :: Games/Entertainment :: Fortune Cookies
Classifier: Topic :: Religion
Classifier: Topic :: Scientific/Engineering :: Mathematics
Project-URL: Bug Tracker, https://github.com/compuuteio/numerology/issues
Project-URL: Documentation, https://github.com/compuuteio/numerology/README.md
Project-URL: Repository, https://github.com/compuuteio/numerology
